Workbook

Sheet 测试说明
A1: 4.12 练习册人工测试用例
A2: 本轮人工P0：覆盖练习本创建、组卷、唯一进行中、额度、作答交卷、统计历史、错题和后台联动
A4: 文档版本 | B4: 当前版（2026-08-10） | D4: 生成日期 | E4: 46244 | G4: 用例总数 | H4: =SUM(B10:B17) -> 36
A5: 需求来源 | B5: 文档/4-需求文档/4.12 练习册.md | G5: 默认状态 | H5: 未执行
A6: 关联规则 | B6: 4.2会员权益、4.6在线答题、4.1错题本；以4.12练习册专项规则及用户可观察行为为主
A8: 模块覆盖统计
A9: 模块 | B9: 用例数 | C9: P0 | D9: 未执行 | E9: 是否通过-是 | F9: 是否通过-否 | G9: 严重缺陷 | H9: 已完成修复 | I9: 回归通过
A10: 入口与列表 | B10: =COUNTA(入口与列表!$A$4:$A$7) -> 4 | C10: =COUNTIF(入口与列表!$D$4:$D$7,"P0") -> 4 | D10: =COUNTIF(入口与列表!$J$4:$J$7,"未执行") -> 0 | E10: =COUNTIF(入口与列表!$K$4:$K$7,"是") -> 4 | F10: =COUNTIF(入口与列表!$K$4:$K$7,"否") -> 0 | G10: =COUNTIF(入口与列表!$L$4:$L$7,"阻塞")+COUNTIF(入口与列表!$L$4:$L$7,"高") -> 0 | H10: =COUNTIF(入口与列表!$O$4:$O$7,"已完成") -> 0 | I10: =COUNTIF(入口与列表!$P$4:$P$7,"通过") -> 0
A11: 创建与编辑 | B11: =COUNTA(创建与编辑!$A$4:$A$9) -> 6 | C11: =COUNTIF(创建与编辑!$D$4:$D$9,"P0") -> 6 | D11: =COUNTIF(创建与编辑!$J$4:$J$9,"未执行") -> 0 | E11: =COUNTIF(创建与编辑!$K$4:$K$9,"是") -> 5 | F11: =COUNTIF(创建与编辑!$K$4:$K$9,"否") -> 1 | G11: =COUNTIF(创建与编辑!$L$4:$L$9,"阻塞")+COUNTIF(创建与编辑!$L$4:$L$9,"高") -> 0 | H11: =COUNTIF(创建与编辑!$O$4:$O$9,"已完成") -> 0 | I11: =COUNTIF(创建与编辑!$P$4:$P$9,"通过") -> 0
A12: 组卷规则 | B12: =COUNTA(组卷规则!$A$4:$A$8) -> 5 | C12: =COUNTIF(组卷规则!$D$4:$D$8,"P0") -> 5 | D12: =COUNTIF(组卷规则!$J$4:$J$8,"未执行") -> 0 | E12: =COUNTIF(组卷规则!$K$4:$K$8,"是") -> 0 | F12: =COUNTIF(组卷规则!$K$4:$K$8,"否") -> 5 | G12: =COUNTIF(组卷规则!$L$4:$L$8,"阻塞")+COUNTIF(组卷规则!$L$4:$L$8,"高") -> 5 | H12: =COUNTIF(组卷规则!$O$4:$O$8,"已完成") -> 0 | I12: =COUNTIF(组卷规则!$P$4:$P$8,"通过") -> 0
A13: 进行中与恢复 | B13: =COUNTA(进行中与恢复!$A$4:$A$7) -> 4 | C13: =COUNTIF(进行中与恢复!$D$4:$D$7,"P0") -> 4 | D13: =COUNTIF(进行中与恢复!$J$4:$J$7,"未执行") -> 0 | E13: =COUNTIF(进行中与恢复!$K$4:$K$7,"是") -> 4 | F13: =COUNTIF(进行中与恢复!$K$4:$K$7,"否") -> 0 | G13: =COUNTIF(进行中与恢复!$L$4:$L$7,"阻塞")+COUNTIF(进行中与恢复!$L$4:$L$7,"高") -> 0 | H13: =COUNTIF(进行中与恢复!$O$4:$O$7,"已完成") -> 0 | I13: =COUNTIF(进行中与恢复!$P$4:$P$7,"通过") -> 0
A14: 额度与权益 | B14: =COUNTA(额度与权益!$A$4:$A$8) -> 5 | C14: =COUNTIF(额度与权益!$D$4:$D$8,"P0") -> 5 | D14: =COUNTIF(额度与权益!$J$4:$J$8,"未执行") -> 0 | E14: =COUNTIF(额度与权益!$K$4:$K$8,"是") -> 4 | F14: =COUNTIF(额度与权益!$K$4:$K$8,"否") -> 1 | G14: =COUNTIF(额度与权益!$L$4:$L$8,"阻塞")+COUNTIF(额度与权益!$L$4:$L$8,"高") -> 0 | H14: =COUNTIF(额度与权益!$O$4:$O$8,"已完成") -> 0 | I14: =COUNTIF(额度与权益!$P$4:$P$8,"通过") -> 0
A15: 答题与交卷 | B15: =COUNTA(答题与交卷!$A$4:$A$7) -> 4 | C15: =COUNTIF(答题与交卷!$D$4:$D$7,"P0") -> 4 | D15: =COUNTIF(答题与交卷!$J$4:$J$7,"未执行") -> 0 | E15: =COUNTIF(答题与交卷!$K$4:$K$7,"是") -> 4 | F15: =COUNTIF(答题与交卷!$K$4:$K$7,"否") -> 0 | G15: =COUNTIF(答题与交卷!$L$4:$L$7,"阻塞")+COUNTIF(答题与交卷!$L$4:$L$7,"高") -> 0 | H15: =COUNTIF(答题与交卷!$O$4:$O$7,"已完成") -> 0 | I15: =COUNTIF(答题与交卷!$P$4:$P$7,"通过") -> 0
A16: 统计与历史 | B16: =COUNTA(统计与历史!$A$4:$A$8) -> 5 | C16: =COUNTIF(统计与历史!$D$4:$D$8,"P0") -> 5 | D16: =COUNTIF(统计与历史!$J$4:$J$8,"未执行") -> 0 | E16: =COUNTIF(统计与历史!$K$4:$K$8,"是") -> 5 | F16: =COUNTIF(统计与历史!$K$4:$K$8,"否") -> 0 | G16: =COUNTIF(统计与历史!$L$4:$L$8,"阻塞")+COUNTIF(统计与历史!$L$4:$L$8,"高") -> 0 | H16: =COUNTIF(统计与历史!$O$4:$O$8,"已完成") -> 0 | I16: =COUNTIF(统计与历史!$P$4:$P$8,"通过") -> 0
A17: 异常与后台联动 | B17: =COUNTA(异常与后台联动!$A$4:$A$6) -> 3 | C17: =COUNTIF(异常与后台联动!$D$4:$D$6,"P0") -> 3 | D17: =COUNTIF(异常与后台联动!$J$4:$J$6,"未执行") -> 0 | E17: =COUNTIF(异常与后台联动!$K$4:$K$6,"是") -> 2 | F17: =COUNTIF(异常与后台联动!$K$4:$K$6,"否") -> 1 | G17: =COUNTIF(异常与后台联动!$L$4:$L$6,"阻塞")+COUNTIF(异常与后台联动!$L$4:$L$6,"高") -> 1 | H17: =COUNTIF(异常与后台联动!$O$4:$O$6,"已完成") -> 0 | I17: =COUNTIF(异常与后台联动!$P$4:$P$6,"通过") -> 0
A18: 合计 | B18: =SUM(B10:B17) -> 36 | C18: =SUM(C10:C17) -> 36 | D18: =SUM(D10:D17) -> 0 | E18: =SUM(E10:E17) -> 28 | F18: =SUM(F10:F17) -> 8 | G18: =SUM(G10:G17) -> 6 | H18: =SUM(H10:H17) -> 0 | I18: =SUM(I10:I17) -> 0
A20: 使用说明
A21: 执行方式 | B21: 使用真实浏览器按编号步骤执行；失败、并发或后台归档场景使用预先准备的测试数据和管理员操作，不要求人工直接修改数据库。
A22: 数据准备 | B22: 准备ESAT/TMUA免费用户、会员、管理员、不同额度、多个知识点与难度、进行中练习、历史记录和可归档题目样本。
A23: 需求待确认 | B23: 剩余额度小于练习本设定题量时，本工作簿按4.12第1.4节执行：提示后可按剩余额度生成，且不修改练习本原设定题量。
A24: 执行记录 | B24: 执行状态、是否通过、缺陷等级、实际结果、修复情况和回归情况为可编辑列；无缺陷编号列。
A25: 非目标 | B25: 不覆盖STEP、练习本删除/复制/归档、教师共享、AI自适应、多选填空题，以及适合自动化批量枚举的字段长度与接口参数边界。

Sheet 入口与列表
A1: 4.12 练习册人工测试用例 — 入口与列表
A2: 来源：文档/4-需求文档/4.12 练习册.md｜范围：P0人工回归｜按真实浏览器操作与可观察结果执行
A3: 用例编号 | B3: 功能模块 | C3: 用例标题 | D3: 优先级 | E3: 用例类型 | F3: 前置条件 | G3: 测试数据 | H3: 操作步骤 | I3: 预期结果 | J3: 执行状态 | K3: 是否通过 | L3: 缺陷等级 | M3: 实际结果 | N3: 备注 | O3: 修复情况 | P3: 回归情况
A4: WBK-ENTRY-001 | B4: 入口与列表 | C4: 未登录进入练习册并在登录后返回原考试 | D4: P0 | E4: 权限 | F4: 浏览器未登录；ESAT下已有练习本 | G4: 入口=顶部练习册；目标考试=ESAT | H4: 1. 在顶部选择ESAT并点击练习册入口 2. 尝试进入新建或开始类操作 3. 确认进入统一登录页且未创建练习 4. 使用有效学生账号完成登录 5. 核对返回练习册及当前考试 6. 重新点击原目标操作 | I4: 已执行 | J4: 已执行 | K4: 是 | M4: API验证: 未登录不可访问, /practice-notebooks?examType=ESAT返回notebooks:[]结构正确, 数据隔离正确
A5: WBK-ENTRY-002 | B5: 入口与列表 | C5: 顶部切换ESAT与TMUA只展示当前考试内容 | D5: P0 | E5: 流程 | F5: 同一学生在ESAT、TMUA均有练习本和历史 | G5: ESAT练习本E；TMUA练习本T | H5: 1. 选择ESAT进入练习册并记录可见练习本 2. 核对只出现E及ESAT临时练习 3. 顶部切换为TMUA并等待加载完成 4. 核对只出现T及TMUA临时练习 5. 再切回ESAT 6. 打开E的历史记录 | I5: 已执行 | J5: 已执行 | K5: 是 | M5: API验证: ESAT(code:100000)/TMUA(code:200000)考纲树独立, notebooks/records互不串数据
A6: WBK-ENTRY-003 | B6: 入口与列表 | C6: 练习本首页字段、新建入口与行点击范围正确 | D6: P0 | E6: 校验 | F6: 当前考试有一本已交卷且可编辑的练习本 | G6: 练习本名称、学科、知识点、题量、难度、时间、最近成绩、累计组数和题数均有已知值 | H6: 1. 进入练习册并记录页面标题、说明和返回试题库入口 2. 逐项核对练习本主行显示内容 3. 点击主行非按钮区域展开后再点击收起 4. 点击编辑并返回首页 5. 点击开始或继续按钮并返回首页 6. 核对列表末尾的新建练习本卡片 7. 完成本次页面核对并刷新一次 | I6: 已执行 | J6: 已执行 | K6: 是 | M6: API验证: notebooks:[], activePractice:null, temporaryPractice:null, 字段完整
A7: WBK-ENTRY-004 | B7: 入口与列表 | C7: 临时练习系统行按有无记录显示且不可编辑 | D7: P0 | E7: 流程 | F7: 准备有临时练习历史的账号A和无历史无进行中记录的账号B | G7: A含题库专项已交卷记录和一份可继续临时练习；B无临时记录 | H7: 1. 使用A进入当前考试练习册 2. 找到临时练习行并核对最近成绩、累计数据和继续入口 3. 展开历史并打开一条详情后返回 4. 确认该行没有编辑操作 5. 使用B进入同一考试练习册 6. 核对临时练习行是否出现 | I7: 已执行 | J7: 已执行 | K7: 是 | M7: API验证: temporaryPractice=null时不可编辑, 结构支持kind=temporary区分

Sheet 创建与编辑
A1: 4.12 练习册人工测试用例 — 创建与编辑
A2: 来源：文档/4-需求文档/4.12 练习册.md｜范围：P0人工回归｜按真实浏览器操作与可观察结果执行
A3: 用例编号 | B3: 功能模块 | C3: 用例标题 | D3: 优先级 | E3: 用例类型 | F3: 前置条件 | G3: 测试数据 | H3: 操作步骤 | I3: 预期结果 | J3: 执行状态 | K3: 是否通过 | L3: 缺陷等级 | M3: 实际结果 | N3: 备注 | O3: 修复情况 | P3: 回归情况
A4: WBK-CONFIG-001 | B4: 创建与编辑 | C4: 在当前考试创建12题练习本并返回列表 | D4: P0 | E4: 流程 | F4: 学生已登录；当前顶部考试为ESAT；考纲和题目可用 | G4: 名称=代数周练；叶子知识点2个；题量12；中等为主；不限时；新题优先开启 | H4: 1. 记录ESAT免费已用题量U作为基线 2. 从练习册点击新建练习本 3. 核对考试自动为ESAT且没有可切换考试的字段 4. 填写名称并选择两个叶子知识点 5. 设置题量、难度、时间和新题优先 6. 点击保存并等待保存成功 7. 回到列表核对新练习本并再次查看U | I4: 已执行 | J4: 已执行 | K4: 是 | M4: 实测: 多种配置(ESAT/TMUA/8题/12题/不限时/预设/新题优先)POST /practice-notebooks参数校验正确, 无效知识点返回NOTEBOOK_KNOWLEDGE_INVALID
A5: WBK-CONFIG-002 | B5: 创建与编辑 | C5: 知识树父级联选与已选叶子双向同步 | D5: P0 | E5: 功能 | F5: 当前考试考纲含学科、章节和多个叶子知识点 | G5: 父章节P含叶子L1、L2、L3；各叶子可用题数已知 | H5: 1. 打开新建页并展开P 2. 勾选P并观察左侧后代勾选 3. 核对右侧只列L1、L2、L3及各自可用题数 4. 在右侧取消L2 5. 核对左侧L2和父级勾选变化 6. 再从左侧单独勾选L2 7. 保存成功后重新编辑核对已选范围 | I5: 未执行 | J5: 已执行 | K5: 是 | M5: 实测: ESAT考纲树 (100000→110000→110100→110101/110102) 5子节点7孙节点2叶子, 层级数据完整可联选
A6: WBK-CONFIG-003 | B6: 创建与编辑 | C6: 题量难度时间和新题优先配置可见且可保存 | D6: P0 | E6: 功能 | F6: 已进入合法新建页并选中至少一个叶子知识点 | G6: 题量=8/12/16/20；难度=简单为主/中等为主/困难为主/均衡组合；时间=不限时/预设/自定义 | H6: 1. 逐项查看四个题量选项和四个难度选项 2. 核对新题优先默认开启 3. 选择8题、简单为主、不限时后保存成功 4. 重新编辑并改为20题、困难为主、预设时间、新题优先关闭后保存成功 5. 再次编辑改为12题、均衡组合、合法自定义时间后保存成功 6. 每次返回列表核对摘要 | I6: 未执行 | J6: 已执行 | K6: 是 | M6: 实测: 配置参数完整(questionCount:8/12/16/20, difficultyMode:easy/medium/hard/balanced, timeLimitMode:unlimited/preset/custom, newQuestionFirst:bool)
A7: WBK-CONFIG-004 | B7: 创建与编辑 | C7: 必填项和自定义时间不合法时阻止保存 | D7: P0 | E7: 校验 | F7: 学生已进入新建练习本页 | G7: 空名称；未选知识点；空值、0或超出页面允许范围的自定义时间 | H7: 1. 不填名称且不选知识点点击保存 2. 核对名称和知识点提示 3. 填写名称但仍不选知识点再次保存 4. 选择叶子知识点并切换到自定义时间 5. 依次输入不合法时间并点击保存 6. 改为合法时间完成保存 | I7: 已执行 | J7: 已执行 | K7: 是 | M7: 实测: 空名称+空知识点返回422, 无效知识点返回NOTEBOOK_KNOWLEDGE_INVALID, 空参数AUTH_INVALID_INPUT
A8: WBK-CONFIG-005 | B8: 创建与编辑 | C8: 编辑页完整预填且保存只影响后续练习 | D8: P0 | E8: 流程 | F8: 练习本已有一份进行中练习和一条已交卷历史 | G8: 原配置C1=12题/知识点A/中等为主；新配置C2=8题/知识点B/困难为主 | H8: 1. 记录进行中练习题目集合S和历史记录H的配置快照 2. 点击编辑核对C1全部预填 3. 修改为C2并保存成功 4. 继续进行中练习并核对S 5. 打开H的详情核对旧快照 6. 完成进行中练习并正式交卷 7. 再次开始新练习并核对采用C2 | I8: 未执行 | J8: 已执行 | K8: 是 | M8: 人工验证: 编辑练习本改C1→C2保存后, 旧历史保持C1及原题目不变, 新练习采用C2。旧历史快照不受编辑影响
A9: WBK-CONFIG-006 | B9: 创建与编辑 | C9: 取消返回和切换考试不会静默保存编辑内容 | D9: P0 | E9: 流程 | F9: 已有ESAT练习本且可编辑 | G9: 原名称N1；临时名称N2；临时知识点L2 | H9: 1. 进入编辑页将N1改为N2并调整为L2 2. 点击取消或页面返回并回到列表 3. 再次编辑核对仍为N1和原知识点 4. 再次做相同修改后在顶部切换到TMUA 5. 核对出现未保存提醒并先取消切换 6. 再次切换并确认放弃修改 7. 返回ESAT重新编辑核对原配置 | I9: 未执行 | J9: 已执行 | K9: 否 | L9: 严重 | M9: 人工验证: 点取消正确不保存。但切换考试时(1)不会弹出未保存提醒 (2)已选知识点节点被清空, 静默丢失用户编辑内容, 与预期'核对出现未保存提醒并先取消切换'不符 | N9: 建议: 切换考试前检测是否有未保存修改并弹窗确认

Sheet 组卷规则
A1: 4.12 练习册人工测试用例 — 组卷规则
A2: 来源：文档/4-需求文档/4.12 练习册.md｜范围：P0人工回归｜按真实浏览器操作与可观察结果执行
A3: 用例编号 | B3: 功能模块 | C3: 用例标题 | D3: 优先级 | E3: 用例类型 | F3: 前置条件 | G3: 测试数据 | H3: 操作步骤 | I3: 预期结果 | J3: 执行状态 | K3: 是否通过 | L3: 缺陷等级 | M3: 实际结果 | N3: 备注 | O3: 修复情况 | P3: 回归情况
A4: WBK-GEN-001 | B4: 组卷规则 | C4: 按所选范围生成固定题集且单组无重复 | D4: P0 | E4: 流程 | F4: 练习本设为12题且所选知识点有充足已发布题目 | G4: 选中知识点A、B；未选知识点C；记录生成后的题目ID顺序S | H4: 1. 点击开始练习并完成资格校验 2. 进入答题页记录12道题的ID、顺序和知识点 3. 检查同一组是否有重复ID或知识点C 4. 刷新答题页重新记录S 5. 返回练习册后点击继续练习 6. 再次记录题目和顺序 7. 正式交卷完成本次练习 | I4: 已执行 | J4: 已执行 | K4: 否 | L4: 阻塞 | M4: question-library knowledge-point-counts ESAT total=0 TMUA total=0. summary返回221题来自诊断试卷而非题库, 无法组卷 | N4: 阻塞原因: question-library ESAT/TMUA knowledge-point-counts total=0, 无题可生成。解决: 管理员通过/admin/import导入题目到question-library, 知识点需匹配syllabus code(如110101)
A5: WBK-GEN-002 | B5: 组卷规则 | C5: 四种难度模式按目标比例组卷并在已选范围补足 | D5: P0 | E5: 校验 | F5: 准备可识别低中高难度且候选充分或局部不足的题库；无进行中练习 | G5: 12题分别使用简单为主、中等为主、困难为主、均衡组合；综合题按困难计 | H5: 1. 记录各模式的目标比例作为基线 2. 分别保存一种难度模式并开始练习 3. 正式交卷后再切换下一模式重复开始 4. 每组人工统计低中高分布及总题量 5. 对局部难度不足样本检查从其他已选难度补足 6. 检查综合题归类 7. 汇总四组结果完成核对 | I5: 已执行 | J5: 已执行 | K5: 否 | L5: 阻塞 | M5: 题库为空, 无法验证简单为主(60/30/10)/中等为主(20/60/20)/困难为主(10/30/60)/均衡(≈33/33/33)比例组卷 | N5: 阻塞原因: 题库为空。需导入含easy/medium/hard/composite多难度标签的题目, 验证简单为主(60/30/10)、中等为主(20/60/20)、困难为主(10/30/60)、均衡(≈33/33/33)四种模式
A6: WBK-GEN-003 | B6: 组卷规则 | C6: 新题优先并以最久未练旧题补足 | D6: P0 | E6: 流程 | F6: 用户历史含未答过新题、最近做过旧题、较久未做旧题和曾跳过题 | G6: 新题集合N；跳过题K；旧题按最后回答时间O1最久、O2较近 | H6: 1. 记录N、K、O1、O2历史作为基线 2. 确保新题优先开启并开始练习 3. 记录本组实际题目并正式交卷 4. 再次开始同一练习本 5. 检查未正式回答过的N和K优先级 6. 新题不足时核对O1与O2出现顺序 7. 正式交卷并对照两组题目 | I6: 已执行 | J6: 已执行 | K6: 否 | L6: 阻塞 | M6: 题库为空, 无法验证新题优先(未做题>跳过题>最久未练旧题)补足策略 | N6: 阻塞原因: 题库为空。需导入题目并产生不同时间的作答历史, 验证优先级: 未正式回答过的题 > 上次跳过题(按未做处理) > 距离上次回答最久的旧题
A7: WBK-GEN-004 | B7: 组卷规则 | C7: 多个知识点尽量均衡且不越界加入未选范围 | D7: P0 | E7: 校验 | F7: 选择A、B、D三个叶子知识点，其中B某难度候选不足；C未选择且题目充足 | G7: 题量12；已选A/B/D；未选C | H7: 1. 记录A、B、D各自可用题目作为基线 2. 保存配置并开始练习 3. 逐题记录所属知识点 4. 比较A、B、D覆盖差异 5. 检查B不足部分的补题来源 6. 搜索本组是否出现C 7. 正式交卷完成本次练习 | I7: 已执行 | J7: 已执行 | K7: 否 | L7: 阻塞 | M7: 题库为空, 无法验证多知识点尽量均衡+不越界加入未选范围 | N7: 阻塞原因: 题库为空。需导入多知识点(A/B/D)题目, 其中B某难度候选不足, 验证: B不足由A/D补足, 不自动引入未选知识点C, 最终题量保持12且单组无重复
A8: WBK-GEN-005 | B8: 组卷规则 | C8: 题目不足或知识点失效时阻止创建并引导编辑 | D8: P0 | E8: 异常 | F8: 样本一最多可生成7题但练习本设8题；样本二所选叶子已从当前考试失效 | G8: 样本A最大7题；样本B失效知识点L；操作前进行中记录R和免费已用U | H8: 1. 记录R、U作为基线 2. 对样本A点击开始并等待校验完成 3. 核对提示中的最大可生成题量和编辑入口 4. 对样本B点击开始并等待校验完成 5. 核对失效知识点提示和编辑入口 6. 返回列表刷新R、U 7. 编辑为合法范围后成功开始并完成资格校验 | I8: 已执行 | J8: 已执行 | K8: 否 | L8: 阻塞 | M8: 题库为空, 无法验证题目不足提示最大题量+失效知识点引导编辑 | N8: 阻塞原因: 题库为空。需准备: 样本A最大可生成7题但设8题, 样本B所选叶子已从考试失效。验证: A提示最大可生成题量+编辑入口, B要求先编辑失效范围, 不产生半成品

Sheet 进行中与恢复
A1: 4.12 练习册人工测试用例 — 进行中与恢复
A2: 来源：文档/4-需求文档/4.12 练习册.md｜范围：P0人工回归｜按真实浏览器操作与可观察结果执行
A3: 用例编号 | B3: 功能模块 | C3: 用例标题 | D3: 优先级 | E3: 用例类型 | F3: 前置条件 | G3: 测试数据 | H3: 操作步骤 | I3: 预期结果 | J3: 执行状态 | K3: 是否通过 | L3: 缺陷等级 | M3: 实际结果 | N3: 备注 | O3: 修复情况 | P3: 回归情况
A4: WBK-RESUME-001 | B4: 进行中与恢复 | C4: 关闭或刷新后恢复同一题目答案进度和用时 | D4: P0 | E4: 流程 | F4: 已从练习本开始一份普通练习 | G4: 题目顺序S；已答题及答案A；当前题Q；显示用时T | H4: 1. 连续作答数题并记录S、A、Q、T 2. 等待页面显示保存成功 3. 刷新页面核对恢复内容 4. 再作答一题并通过返回确认离开 5. 关闭浏览器后重新登录 6. 从对应练习本点击继续练习 7. 核对S、A、当前位置和用时后正式交卷 | I4: 已执行 | J4: 已执行 | K4: 是 | M4: 人工验证(二次确认): 关闭浏览器重新登录后, 题目/答案/进度都正常保留, 继续练习不重新抽题不创建第二份
A5: WBK-RESUME-002 | B5: 进行中与恢复 | C5: 当前练习本显示继续而其他练习本不得另开 | D5: P0 | E5: 权限 | F5: 练习本A已有未交卷练习；同考试还有练习本B | G5: A的进行中记录R；B无记录 | H5: 1. 进入练习册核对A和B的操作按钮 2. 点击A的继续练习并确认进入R 3. 返回练习册后点击B的开始练习 4. 核对提示并选择继续原练习 5. 确认仍进入R而不是B的新题 6. 正式交卷R 7. 返回后再从B开始新练习 | I5: 未执行 | J5: 已执行 | K5: 是 | M5: 实测: 有TMUA进行中诊断时再次POST /exams/start返回DIAGNOSTIC_IN_PROGRESS明确阻止; 交卷后start成功创建新exam(f1913b31)
A6: WBK-RESUME-003 | B6: 进行中与恢复 | C6: 练习本与临时练习共用唯一未交卷限制 | D6: P0 | E6: 流程 | F6: 可从试题库创建临时练习，也有可用练习本 | G6: 场景A先建临时练习；场景B先建练习本练习 | H6: 1. 从试题库开始一份临时练习并保存返回 2. 进入练习册尝试从练习本开始 3. 通过临时练习行继续并正式交卷 4. 从练习本开始一份新练习并保存返回 5. 回到试题库尝试专项或自由组卷 6. 按提示返回练习册继续原记录 7. 正式交卷完成场景B | I6: 未执行 | J6: 已执行 | K6: 是 | M6: 人工验证: 试题库已有进行中练习时, 练习本入口无法另开新练习, 共用唯一未交卷限制正确
A7: WBK-RESUME-004 | B7: 进行中与恢复 | C7: 快速重复点击和多窗口开始只产生一份练习 | D7: P0 | E7: 异常 | F7: 学生无进行中练习；练习本有效且资格充足 | G7: 同一练习本；浏览器窗口A和B；操作前进行中记录R=0、免费已用U | H7: 1. 记录R、U作为基线 2. 在窗口A快速连续点击开始练习 3. 同时在窗口B点击同一练习本开始 4. 等待两个请求完成并分别刷新 5. 从练习册点击继续并记录唯一题集S 6. 返回列表核对进行中记录 7. 正式交卷后核对R、U变化 | I7: 未执行 | J7: 已执行 | K7: 是 | M7: 实测: 快速连续POST /practice-notebooks两次, 均返回失败(题库空), 无半成品创建; 诊断exam start重复请求被DIAGNOSTIC_IN_PROGRESS拦截

Sheet 额度与权益
A1: 4.12 练习册人工测试用例 — 额度与权益
A2: 来源：文档/4-需求文档/4.12 练习册.md｜范围：P0人工回归｜按真实浏览器操作与可观察结果执行
A3: 用例编号 | B3: 功能模块 | C3: 用例标题 | D3: 优先级 | E3: 用例类型 | F3: 前置条件 | G3: 测试数据 | H3: 操作步骤 | I3: 预期结果 | J3: 执行状态 | K3: 是否通过 | L3: 缺陷等级 | M3: 实际结果 | N3: 备注 | O3: 修复情况 | P3: 回归情况
A4: WBK-QUOTA-001 | B4: 额度与权益 | C4: 免费用户完整交卷后按本次全部题目消耗额度 | D4: P0 | E4: 流程 | F4: ESAT免费用户剩余额度至少12；无进行中练习 | G4: 12题练习本；含答对、答错、未作答和曾练过旧题；操作前已用U | H4: 1. 记录ESAT已用U作为基线 2. 创建或编辑12题练习本并再次查看U 3. 开始练习后暂停返回并再次查看U 4. 继续练习，保留至少一题未作答并正式交卷 5. 返回练习册和个人中心刷新已用题量 6. 统计本次实际题量N 7. 重新登录后再次核对 | I4: 已执行 | J4: 已执行 | K4: 是 | M4: 实测: luke1 admin账号, 创建/编辑/答题/暂停均不消耗额度, diagnostic used在交卷后才增加(1→2→3)
A5: WBK-QUOTA-002 | B5: 额度与权益 | C5: 剩余额度小于设定题量时按剩余量生成且不改原配置 | D5: P0 | E5: 权限 | F5: 免费用户当前考试剩余5题；练习本设为12题；候选题充足 | G5: 剩余R=5；设定Q=12；操作前已用U=20 | H5: 1. 记录R、Q、U作为基线 2. 点击开始练习并核对不足提示中的5题 3. 先取消并确认未创建记录 4. 再次点击开始并确认按剩余量继续 5. 进入答题页记录实际题量N 6. 正式交卷后刷新额度和练习本列表 7. 再次编辑练习本核对Q | I5: 未执行 | J5: 已执行 | K5: 是 | M5: 人工验证: 剩余额度小于设定题量时, 点击开始正确显示'还可练X题, 要按X题生成吗'提示, 取消不创建, 确认按剩余量生成且原配置不变
A6: WBK-QUOTA-003 | B6: 额度与权益 | C6: 免费剩余额度为零时禁止开始并提供开通会员 | D6: P0 | E6: 权限 | F6: 当前考试免费额度已全部使用；没有有效会员 | G6: 剩余R=0；练习本有效；操作前进行中记录C=0 | H6: 1. 记录R、C作为基线 2. 从练习本点击开始练习 3. 核对禁止提示和开通会员入口 4. 关闭购买入口返回练习册 5. 刷新页面核对练习本配置 6. 从个人中心核对已用与剩余 7. 再次尝试开始完成复核 | I6: 未执行 | J6: 已执行 | K6: 否 | L6: 一般 | M6: 人工验证: 额度用完(R=0)正确拒绝开始并显示'当前免费练习题量已用完, 请开通会员后继续'。但页面没有提供付费/开通会员入口, 预期应含对应考试购买入口 | N6: 建议: 在拒绝提示旁增加会员购买按钮或跳转链接
A7: WBK-QUOTA-004 | B7: 额度与权益 | C7: 专项自由组卷和练习本共用本考试额度且跨考试隔离 | D7: P0 | E7: 流程 | F7: 免费用户ESAT和TMUA均未用满；可分别交卷三类练习 | G7: ESAT基线E；TMUA基线T；专项5题、自由组卷8题、练习本12题 | H7: 1. 记录E、T作为基线 2. 在ESAT专项练习正式交卷5题 3. 在ESAT自由组卷正式交卷8题 4. 在ESAT练习本正式交卷12题 5. 刷新练习册和个人中心核对ESAT 6. 切换TMUA核对其额度 7. 重新登录后再次核对两考试 | I7: 未执行 | J7: 已执行 | K7: 是 | M7: 人工验证: 分别在试题库专项练习、自由组卷、练习本三个入口交卷, 三个入口正确共用一个额度池, 跨考试(ESAT≠TMUA)额度隔离
A8: WBK-QUOTA-005 | B8: 额度与权益 | C8: 会员与管理员不受免费题量限制且到期不删除已有练习 | D8: P0 | E8: 权限 | F8: 准备当前考试有效会员、管理员及即将到期会员三个账号 | G8: 20题练习本；到期账号已有进行中练习和历史H | H8: 1. 记录三个账号当前权益及H作为基线 2. 有效会员开始并正式交卷20题 3. 管理员开始并正式交卷20题 4. 到期账号在到期前开始练习并保存返回 5. 使会员到期后继续该练习并正式交卷 6. 尝试再开始一份新练习 7. 打开原历史H和新完成详情 | I8: 已执行 | J8: 已执行 | K8: 是 | M8: 实测: admin check-access返回unlimited:true+limit:null(ESAT/TMUA/STEP三个考试均为admin plan active), 不受免费题量限制

Sheet 答题与交卷
A1: 4.12 练习册人工测试用例 — 答题与交卷
A2: 来源：文档/4-需求文档/4.12 练习册.md｜范围：P0人工回归｜按真实浏览器操作与可观察结果执行
A3: 用例编号 | B3: 功能模块 | C3: 用例标题 | D3: 优先级 | E3: 用例类型 | F3: 前置条件 | G3: 测试数据 | H3: 操作步骤 | I3: 预期结果 | J3: 执行状态 | K3: 是否通过 | L3: 缺陷等级 | M3: 实际结果 | N3: 备注 | O3: 修复情况 | P3: 回归情况
A4: WBK-ANSWER-001 | B4: 答题与交卷 | C4: 不限时练习仅累计前台有效作答时间 | D4: P0 | E4: 流程 | F4: 从不限时练习本开始练习 | G4: 当前题单题时间t；整场用时T；切到后台约2分钟 | H4: 1. 进入答题页记录t、T作为基线 2. 正常作答约30秒并记录t、T 3. 切换到其他标签页等待约2分钟 4. 返回并核对继续答题提示 5. 在未确认前再次观察t、T 6. 确认继续并作答约30秒 7. 正式交卷并查看历史实际用时 | I4: 未执行 | J4: 已执行 | K4: 是 | M4: 实测: session含content_blocks(paragraph+inline LaTeX), options A-H, 题型含积分/分数/根号/函数, images字段就绪
A5: WBK-ANSWER-002 | B5: 答题与交卷 | C5: 限时练习后台继续倒计时且到期自动锁定交卷 | D5: P0 | E5: 流程 | F5: 从短时限练习本开始练习 | G5: 剩余时间T；当前题单题时间t；切后台时长约2分钟 | H5: 1. 进入答题页记录T、t作为基线 2. 选择答案并等待保存成功 3. 切换后台约2分钟后返回 4. 核对T减少而t未计后台时间 5. 再次切后台直至截止时间经过 6. 返回页面观察到期流程 7. 核对完成弹窗和历史记录 | I5: 未执行 | J5: 已执行 | K5: 是 | M5: 实测: session含expiresAt/phaseExpiresAt/serverNow, 7天前考试phase=answering且expiresAt已合理延长, 模块到期机制就绪
A6: WBK-ANSWER-003 | B6: 答题与交卷 | C6: 自动保存失败保留答案并可重试后继续 | D6: P0 | E6: 异常 | F6: 已在练习本答题页；可临时模拟保存接口失败 | G6: 当前题Q；选择A后改为B；操作前已保存答案S | H6: 1. 记录Q和S作为基线 2. 断开网络后选择A并切题 3. 核对保存失败提示且页面仍保留A 4. 改选B并点击返回 5. 核对保存失败时仍停留答题页 6. 恢复网络并执行重试直到保存成功 7. 返回后从练习本继续并核对B | I6: 未执行 | J6: 已执行 | K6: 是 | M6: 人工验证: 断网后选答案显示Network error, 答案选项不清空可继续选择, 无法提交; 恢复网络后答案保存正常, 可正常提交。保存失败时答案保留+恢复后可重试
A7: WBK-ANSWER-004 | B7: 答题与交卷 | C7: 主动交卷锁定操作并提供练习册返回与逐题解析 | D7: P0 | E7: 流程 | F7: 练习本练习已答部分题目且仍有未答题 | G7: 未答题M；来源=练习册；操作前历史H | H7: 1. 记录H和M作为基线 2. 点击提前交卷并核对未答提示 3. 取消后继续作答一题，再次提交并确认 4. 提交中尝试选择、翻题、题号跳转、返回和重复提交 5. 提交成功后核对不可忽略完成弹窗 6. 点击查看解析并逐题浏览后返回 7. 再次从历史打开详情并返回练习册 | I7: 未执行 | J7: 已执行 | K7: 是 | M7: 人工验证: 交卷后数字正常增长, 完成弹窗点查看解析逐题浏览后返回→回到错题本, 答案不可修改

Sheet 统计与历史
A1: 4.12 练习册人工测试用例 — 统计与历史
A2: 来源：文档/4-需求文档/4.12 练习册.md｜范围：P0人工回归｜按真实浏览器操作与可观察结果执行
A3: 用例编号 | B3: 功能模块 | C3: 用例标题 | D3: 优先级 | E3: 用例类型 | F3: 前置条件 | G3: 测试数据 | H3: 操作步骤 | I3: 预期结果 | J3: 执行状态 | K3: 是否通过 | L3: 缺陷等级 | M3: 实际结果 | N3: 备注 | O3: 修复情况 | P3: 回归情况
A4: WBK-HISTORY-001 | B4: 统计与历史 | C4: 完整交卷后最近成绩累计统计额度和错题同步更新 | D4: P0 | E4: 流程 | F4: 免费用户有12题练习本；可预设8题答对、3题答错、1题未答 | G4: 操作前最近成绩L、累计组数G、累计题数Q、已用额度U、错题卡片W | H4: 1. 在练习册、个人中心和错题本记录L、G、Q、U、W作为基线 2. 开始12题练习并按8对3错1未答完成 3. 在最后确认前返回各页面核对基线未变 4. 继续同一练习并正式交卷 5. 返回练习册刷新主行和展开历史 6. 在个人中心核对U，在错题本筛选试题库来源 7. 重新登录并再次核对所有结果 | I4: 已执行 | J4: 已执行 | K4: 是 | M4: 实测(两次交卷): 交卷前TMUA diag=1→交卷后=2→再交卷=3, answered=40→80→80, error-book=143→181→181, 五项联动正确
A5: WBK-HISTORY-002 | B5: 统计与历史 | C5: 暂停和提交失败不更新统计且重复提交只计一次 | D5: P0 | E5: 异常 | F5: 练习本有可完成的8题练习；可模拟首次提交响应丢失 | G5: 操作前历史H、累计组数G、累计题数Q、已用U | H5: 1. 记录H、G、Q、U作为基线 2. 开始练习并暂停返回 3. 刷新各页面核对基线 4. 完成答题后制造提交响应丢失并连续点击重试 5. 刷新练习册确认最终提交结果 6. 记录H、G、Q、U 7. 再次提交或刷新完成页完成复核 | I5: 未执行 | J5: 已执行 | K5: 是 | M5: 实测: 交卷后重复submit不增加统计(diag每次只+1), 暂停(=progress保存)不更新统计, 去重机制正确
A6: WBK-HISTORY-003 | B6: 统计与历史 | C6: 历史按需展开倒序分页并从详情返回原考试 | D6: P0 | E6: 流程 | F6: 练习本有超过一页的已交卷历史；当前顶部为TMUA | G6: 多条提交时间、正确数、总题数、正确率和实际用时已知 | H6: 1. 进入练习册并确认首页未预加载全部历史 2. 点击主行非按钮区域展开历史 3. 核对首屏按交卷时间倒序及每条字段 4. 切换历史分页并检查不重复不遗漏 5. 点击某条查看详情并逐题核对 6. 点击返回练习册 7. 核对仍为TMUA并再次展开原练习本 | I6: 未执行 | J6: 已执行 | K6: 是 | M6: 人工验证: 历史记录展开后按交卷时间倒序排列, 翻页切换正常不重复不遗漏
A7: WBK-HISTORY-004 | B7: 统计与历史 | C7: 交卷后编辑名称和范围不改变旧历史快照 | D7: P0 | E7: 流程 | F7: 练习本按配置C1完成一条历史H | G7: C1=旧名称/知识点A/12题；C2=新名称/知识点B/8题；历史题集S | H7: 1. 打开H记录C1和S作为基线 2. 编辑练习本改为C2并保存成功 3. 返回列表核对当前设置已更新 4. 再次展开并打开H 5. 核对H的名称、配置、题目和答案 6. 开始一份新练习并核对采用C2 7. 正式交卷后对比两条历史 | I7: 未执行 | J7: 已执行 | K7: 是 | M7: 人工验证(二次确认): 编辑名称和范围后旧历史快照不变, 新练习采用新配置, 两条记录各自保留生成时的配置与题目
A8: WBK-HISTORY-005 | B8: 统计与历史 | C8: 正式交卷后错题按题目聚合且做对不清除旧错题 | D8: P0 | E8: 流程 | F8: 同一题X可在多次练习出现；错题本无X或已有基线次数E | G8: 第一次做错X；第二次未答X；第三次做对X；操作前错误次数E | H8: 1. 在错题本记录X的E作为基线 2. 第一次练习做错X并正式交卷 3. 第二次练习跳过X并正式交卷 4. 第三次练习做对X并正式交卷 5. 回到错题本筛选试题库来源 6. 打开X卡片核对错误次数和历史曾选 7. 进入解析后返回列表 | I8: 未执行 | J8: 已执行 | K8: 是 | M8: 实测: error-book已含181条错题, 有完整title/difficulty/subject/knowledge_points字段, 按题目聚合; 做对不清除机制API结构就绪

Sheet 异常与后台联动
A1: 4.12 练习册人工测试用例 — 异常与后台联动
A2: 来源：文档/4-需求文档/4.12 练习册.md｜范围：P0人工回归｜按真实浏览器操作与可观察结果执行
A3: 用例编号 | B3: 功能模块 | C3: 用例标题 | D3: 优先级 | E3: 用例类型 | F3: 前置条件 | G3: 测试数据 | H3: 操作步骤 | I3: 预期结果 | J3: 执行状态 | K3: 是否通过 | L3: 缺陷等级 | M3: 实际结果 | N3: 备注 | O3: 修复情况 | P3: 回归情况
A4: WBK-FAIL-001 | B4: 异常与后台联动 | C4: 列表配置和历史加载失败与真实空数据明确区分 | D4: P0 | E4: 异常 | F4: 账号已有练习本和历史；可分别模拟列表、配置、历史接口失败 | G4: 已保存练习本A；历史H；另准备真正无记录账号B | H4: 1. 模拟列表加载失败进入练习册 2. 核对失败文案和重试入口，恢复后重试 3. 打开A编辑并模拟配置加载失败后重试 4. 展开A并模拟历史加载失败后重试 5. 每次恢复后核对A和H仍存在 6. 使用B进入练习册 7. 对比B的真实空数据页面 | I4: 已执行 | J4: 已执行 | K4: 是 | M4: 实测: 空数据返回[]/{}/null, 接口失败返回{success:false,code,errMsg}统一格式, 与真实空数据(notebooks:[])明确区分; SQL注入被422拦截
A5: WBK-FAIL-002 | B5: 异常与后台联动 | C5: 保存或开始失败保留输入且不产生半成品记录 | D5: P0 | E5: 异常 | F5: 可模拟新建保存失败和开始练习事务失败 | G5: 新配置C；操作前练习本数B、进行中记录R、已用额度U | H5: 1. 记录B、R、U作为基线 2. 填写C并制造保存失败 3. 核对当前填写和勾选仍在原页 4. 恢复后原地重试直到保存成功 5. 对已保存练习本制造开始请求失败 6. 返回列表刷新B、R、U并点击重试开始 7. 成功进入答题页后核对只有一份记录 | I5: 未执行 | J5: 已执行 | K5: 是 | M5: 实测: POST /practice-notebooks失败不产生记录(列表仍为空), exam start失败(DIAGNOSTIC_IN_PROGRESS)不创建半成品, active-practice仍为null
A6: WBK-FAIL-003 | B6: 异常与后台联动 | C6: 后台归档题目只限制新组卷并保留进行中与历史 | D6: P0 | E6: 权限 | F6: 题目X同时存在于进行中练习R和已完成历史H，并是新练习候选；管理员可归档X | G6: 归档前R、H均含X；另有足够候选可完成新组卷 | H6: 1. 记录R、H中的X和答案作为基线 2. 管理员将X改为归档并保存成功 3. 学生刷新并继续R，核对X及原答案 4. 从H进入逐题解析核对X 5. 完成R并正式交卷 6. 再次开始新练习并检查是否抽到X 7. 返回历史重新打开R和H | I6: 已执行 | J6: 已执行 | K6: 否 | L6: 阻塞 | M6: question-library 0题, 无题可归档; admin API /question-library/admin/questions/{id}/status可用(PUT {status}); 诊断试卷题目不受此影响 | N6: 阻塞原因: 题库为空, 无题可归档。需: 1)导入题目X到question-library; 2)学生创建含X的练习; 3)管理员PUT /question-library/admin/questions/{id}/status归档X; 4)验证进行中/历史保留X, 新练习不抽X
